pyrexpaint/__init__.py
pyrexpaint-0.0.2.dist-info/LICENSE.md
pyrexpaint-0.0.2.dist-info/METADATA
pyrexpaint-0.0.2.dist-info/WHEEL
pyrexpaint-0.0.2.dist-info/top_level.txt
pyrexpaint-0.0.2.dist-info/RECORD
