Metadata-Version: 2.1
Name: pyrexpaint
Version: 0.0.2
Summary: A small library for loading REXPaint .xp files.
Home-page: https://github.com/mattlink/pyrexpaint
Author: Matt Link
Project-URL: Bug Tracker, https://github.com/mattlink/pyrexpaint/issues
Classifier: Programming Language :: Python :: 3
Classifier: License :: OSI Approved :: MIT License
Classifier: Operating System :: OS Independent
Requires-Python: >=3.6
License-File: LICENSE.md
